Metadata-Version: 2.1
Name: aesqlapius
Version: 0.0.9
Summary: Manage SQL queries as a Python API
Home-page: https://github.com/AMDmi3/aesqlapius
Author: Dmitry Marakasov
Author-email: amdmi3@amdmi3.ru
License: MIT
Platform: UNKNOWN
Classifier: Development Status :: 3 - Alpha
Classifier: Intended Audience :: Developers
Classifier: License :: OSI Approved :: MIT License
Classifier: Programming Language :: Python :: 3 :: Only
Classifier: Programming Language :: Python :: 3.9
Classifier: Programming Language :: Python :: 3.10
Classifier: Programming Language :: SQL
Classifier: Topic :: Database
Requires-Python: >=3.9
License-File: LICENSE
